llmscope/__init__.py
llmscope-0.1.1.dist-info/METADATA
llmscope-0.1.1.dist-info/WHEEL
llmscope-0.1.1.dist-info/licenses/LICENSE
llmscope-0.1.1.dist-info/RECORD
