Metadata-Version: 2.4
Name: llmscope
Version: 0.1.1
Summary: a Python library designed to simplify interactions with Large Language Models (LLMs) by providing a stateful, fluent interface for managing conversation history, tool usage, and response parsing. It leverages libraries like `mirascope` for LLM calls and `pydantic` for data validation and parsing.
Author-email: Yuantian Ding <dnailzb@outlook.com>
License-File: LICENSE
Requires-Python: >=3.8
Requires-Dist: mirascope>=1.22.4
Requires-Dist: textwrap3>=0.9.2
Provides-Extra: anthropic
Requires-Dist: mirascope[anthropic]>=1.22.4; extra == 'anthropic'
Provides-Extra: azure
Requires-Dist: mirascope[azure]>=1.22.4; extra == 'azure'
Provides-Extra: bedrock
Requires-Dist: mirascope[bedrock]>=1.22.4; extra == 'bedrock'
Provides-Extra: cohere
Requires-Dist: mirascope[cohere]>=1.22.4; extra == 'cohere'
Provides-Extra: google
Requires-Dist: mirascope[google]>=1.22.4; extra == 'google'
Provides-Extra: groq
Requires-Dist: mirascope[groq]>=1.22.4; extra == 'groq'
Provides-Extra: litellm
Requires-Dist: mirascope[litellm]>=1.22.4; extra == 'litellm'
Provides-Extra: openai
Requires-Dist: mirascope[openai]>=1.22.4; extra == 'openai'
Provides-Extra: xai
Requires-Dist: mirascope[xai]>=1.22.4; extra == 'xai'
